MANIFEST.in
pavement.py
paver-minilib.zip
setup.py
PydapSearch.egg-info/PKG-INFO
PydapSearch.egg-info/SOURCES.txt
PydapSearch.egg-info/dependency_links.txt
PydapSearch.egg-info/entry_points.txt
PydapSearch.egg-info/namespace_packages.txt
PydapSearch.egg-info/not-zip-safe
PydapSearch.egg-info/requires.txt
PydapSearch.egg-info/top_level.txt
pydap/__init__.py
pydap/wsgi/__init__.py
pydap/wsgi/search.py